psf_analysis_CFIM/__init__.py
psf_analysis_CFIM/_dock_widget.py
psf_analysis_CFIM/bead_finder_CFIM.py
psf_analysis_CFIM/image_selector_dropdown.py
psf_analysis_CFIM/mounting_medium_selector.py
psf_analysis_CFIM/napari.yaml
psf_analysis_CFIM/points_dropdown.py
psf_analysis_CFIM/range_indicator_button.py
psf_analysis_CFIM/config/__init__.py
psf_analysis_CFIM/config/settings_model.py
psf_analysis_CFIM/config/settings_widget.py
psf_analysis_CFIM/czi_reader/__init__.py
psf_analysis_CFIM/czi_reader/czi_metadata_processor.py
psf_analysis_CFIM/czi_reader/czi_reader_CFIM.py
psf_analysis_CFIM/debug/__init__.py
psf_analysis_CFIM/debug/debug.py
psf_analysis_CFIM/debug/global_vars.py
psf_analysis_CFIM/error_widget/__init__.py
psf_analysis_CFIM/error_widget/error_display_widget.py
psf_analysis_CFIM/library_workarounds/MultiKeyDict.py
psf_analysis_CFIM/library_workarounds/QDualSeperatorValidator.py
psf_analysis_CFIM/library_workarounds/QLineEditWithColormapBg.py
psf_analysis_CFIM/library_workarounds/QPushButton.py
psf_analysis_CFIM/library_workarounds/RangeDict.py
psf_analysis_CFIM/library_workarounds/__init__.py
psf_analysis_CFIM/psf_analysis/__init__.py
psf_analysis_CFIM/psf_analysis/analyzer.py
psf_analysis_CFIM/psf_analysis/image.py
psf_analysis_CFIM/psf_analysis/image_analysis.py
psf_analysis_CFIM/psf_analysis/parameters.py
psf_analysis_CFIM/psf_analysis/psf.py
psf_analysis_CFIM/psf_analysis/records.py
psf_analysis_CFIM/psf_analysis/sample.py
psf_analysis_CFIM/psf_analysis/utils.py
psf_analysis_CFIM/psf_analysis/extract/BeadExtractor.py
psf_analysis_CFIM/psf_analysis/extract/__init__.py
psf_analysis_CFIM/psf_analysis/fit/__init__.py
psf_analysis_CFIM/psf_analysis/fit/estimator.py
psf_analysis_CFIM/psf_analysis/fit/fit_1d.py
psf_analysis_CFIM/psf_analysis/fit/fit_2d.py
psf_analysis_CFIM/psf_analysis/fit/fit_3d.py
psf_analysis_CFIM/psf_analysis/fit/fitter.py
psf_analysis_CFIM/report_widget/__init__.py
psf_analysis_CFIM/report_widget/report_widget.py
psf_analysis_cfim-1.7.9.dist-info/licenses/LICENSE
psf_analysis_cfim-1.7.9.dist-info/METADATA
psf_analysis_cfim-1.7.9.dist-info/WHEEL
psf_analysis_cfim-1.7.9.dist-info/entry_points.txt
psf_analysis_cfim-1.7.9.dist-info/top_level.txt
psf_analysis_cfim-1.7.9.dist-info/RECORD
