Metadata-Version: 2.4
Name: psf-analysis-CFIM
Version: 1.7.9
Summary: A continuation of napari_psf_analysis, developed for CFIM - KU
Home-page: https://github.com/MaxusTheOne/napari-psf-analysis-CFIM-edition
Author: Markus L. Bille
Author-email: github+Markus@bille.dk
License: BSD-3-Clause
Project-URL: Documentation, https://github.com/MaxusTheOne/napari-psf-analysis-CFIM-edition#README.md
Project-URL: Source Code, https://github.com/MaxusTheOne/napari-psf-analysis-CFIM-edition
Project-URL: Issue Tracker, https://github.com/MaxusTheOne/napari-psf-analysis-CFIM-edition/issues
Classifier: Development Status :: 5 - Production/Stable
Classifier: Framework :: napari
Classifier: Intended Audience :: Science/Research
Classifier: License :: OSI Approved :: BSD License
Classifier: Operating System :: OS Independent
Classifier: Programming Language :: Python
Classifier: Topic :: Scientific/Engineering :: Image Processing
Classifier: Topic :: Scientific/Engineering :: Bio-Informatics
Classifier: Topic :: Scientific/Engineering :: Visualization
Requires-Python: >=3.9
License-File: LICENSE
Requires-Dist: aicsimageio
Requires-Dist: aicspylibczi
Requires-Dist: bfio
Requires-Dist: matplotlib<3.9
Requires-Dist: matplotlib-inline
Requires-Dist: matplotlib-scalebar
Requires-Dist: napari[all]<0.6
Requires-Dist: numpy<2.0,>=1.26
Requires-Dist: pandas
Requires-Dist: pydantic
Requires-Dist: PyYAML
Requires-Dist: QtPy
Requires-Dist: scipy
Requires-Dist: reportlab
Provides-Extra: testing
Requires-Dist: napari; extra == "testing"
Requires-Dist: pyqt5; extra == "testing"
Requires-Dist: tox; extra == "testing"
Dynamic: license-file
